flight/DBCV.py
flight/__init__.py
flight/distance.py
flight/flight.py
flight/hierarchy.py
flight/metrics.py
flight/utils.py
flight/lorikeet/__init__.py
flight/lorikeet/cluster.py
flight/rosella/__init__.py
flight/rosella/binning.py
flight/rosella/clustering.py
flight/rosella/embedding.py
flight/rosella/rosella.py
flight/rosella/validating.py
flight_genome-1.6.3.data/data/LICENSE
flight_genome-1.6.3.data/data/README.md
flight_genome-1.6.3.dist-info/LICENSE
flight_genome-1.6.3.dist-info/METADATA
flight_genome-1.6.3.dist-info/WHEEL
flight_genome-1.6.3.dist-info/entry_points.txt
flight_genome-1.6.3.dist-info/top_level.txt
flight_genome-1.6.3.dist-info/RECORD
