Metadata-Version: 2.1
Name: flight-genome
Version: 1.6.3
Summary: flight - metagenomic binner and variant clusterer.
Home-page: https://github.com/rhysnewell/flight
Author: Rhys Newell
Author-email: rhys.newell94@gmail.com
License: BSD-3
Classifier: Topic :: Scientific/Engineering :: Bio-Informatics
License-File: LICENSE
Requires-Dist: umap-learn >=0.5.3
Requires-Dist: numpy <=1.24
Requires-Dist: scikit-learn <=1.1,>=1.0.2
Requires-Dist: scipy <=1.11
Requires-Dist: scikit-bio >=0.5.7
Requires-Dist: numba <=0.57,>=0.53
Requires-Dist: pandas >=1.3
Requires-Dist: pynndescent >=0.5.7
Requires-Dist: hdbscan >=0.8.28
Requires-Dist: joblib <=1.3.0
Requires-Dist: pebble
Requires-Dist: threadpoolctl
Requires-Dist: imageio
Requires-Dist: matplotlib
Requires-Dist: seaborn
Requires-Dist: tqdm
Requires-Dist: tbb
Requires-Dist: biopython
